{
    "id": "laugh-explosion",
    "name": "爆笑大字爆炸",
    "description": "《一见你就笑》风格爆笑反应大字特效，漫画爆炸云底板 + 极速线 + 震动波 + 笑哭表情，适用于【笑死我了】【绝了】【好会玩】等情绪爆发场景",
    "level": "advanced",
    "tags": [
        "variety",
        "comedy",
        "laugh",
        "explosion",
        "cartoon",
        "reaction",
        "emotional",
        "chinese"
    ],
    "category": "variety-comedy",
    "language": "zh",
    "textDefaults": {
        "text": "笑死我了",
        "fontSizeRange": [
            80,
            140
        ],
        "recommendLines": 1,
        "fontFamily": [
            "Zcool KuaiLe",
            "Zcool QingKe HuangYou",
            "PingFang SC",
            "Microsoft YaHei",
            "sans-serif"
        ],
        "stroke": {
            "enabled": true,
            "color": "#FFFFFF",
            "width": 8
        },
        "shadow": {
            "enabled": true,
            "color": "rgba(45, 27, 78, 0.5)",
            "blur": 10,
            "offsetX": 4,
            "offsetY": 4
        }
    },
    "colorPresets": [
        {
            "id": "lmao-yellow",
            "name": "笑疯黄",
            "gradient": "linear-gradient(180deg, #FFE135 0%, #FF8C00 50%, #FF6B9D 100%)",
            "strokeColor": "#FFFFFF",
            "outerStrokeColor": "#2D1B4E",
            "plateColor": "#FFE135",
            "glowColor": "#FFE135"
        },
        {
            "id": "rofl-pink",
            "name": "笑翻粉",
            "gradient": "linear-gradient(180deg, #FFFFFF 0%, #FF6B9D 50%, #7C3AED 100%)",
            "strokeColor": "#FFFFFF",
            "outerStrokeColor": "#4A1942",
            "plateColor": "#FF6B9D",
            "glowColor": "#FF6B9D"
        },
        {
            "id": "dead-blue",
            "name": "笑死蓝",
            "gradient": "linear-gradient(180deg, #FFFFFF 0%, #00D4FF 50%, #0066FF 100%)",
            "strokeColor": "#FFFFFF",
            "outerStrokeColor": "#003366",
            "plateColor": "#00D4FF",
            "glowColor": "#00D4FF"
        },
        {
            "id": "crazy-rainbow",
            "name": "疯狂彩虹",
            "gradient": "linear-gradient(90deg, #FF6B9D 0%, #FFE135 25%, #7CFC00 50%, #00D4FF 75%, #7C3AED 100%)",
            "strokeColor": "#FFFFFF",
            "outerStrokeColor": "#2D1B4E",
            "plateColor": "#FFE135",
            "glowColor": "#FFE135"
        }
    ],
    "rendering": {
        "aspectRatio": 2.5,
        "heightRatio": 0.6,
        "duration": 1.5,
        "frameRate": 30
    },
    "compat": {
        "renderer": "canvas-fancy-text",
        "scenePath": "laugh-explosion.scene"
    }
}









